windowshap/__init__.py
windowshap/windowshap.py
windowshap-1.0.1.dist-info/METADATA
windowshap-1.0.1.dist-info/WHEEL
windowshap-1.0.1.dist-info/licenses/LICENSE
windowshap-1.0.1.dist-info/RECORD
