Metadata-Version: 2.1
Name: windowshap
Version: 1.0.1
Summary: an effective explanation method for time-series classifiers.
Author-email: Shashank Yadav <shashank@arizona.edu>
License-File: LICENSE
Classifier: License :: OSI Approved :: MIT License
Classifier: Operating System :: OS Independent
Classifier: Programming Language :: Python :: 3
Requires-Python: >=3.7
